MANIFEST.in
README.md
setup.py
streamlit_ketchersa/__init__.py
streamlit_ketchersa/pypi_readme.md
streamlit_ketchersa.egg-info/PKG-INFO
streamlit_ketchersa.egg-info/SOURCES.txt
streamlit_ketchersa.egg-info/dependency_links.txt
streamlit_ketchersa.egg-info/requires.txt
streamlit_ketchersa.egg-info/top_level.txt
streamlit_ketchersa/frontend/dist/index.html
streamlit_ketchersa/frontend/dist/vite.svg
streamlit_ketchersa/frontend/dist/Ketcher v2.9.0_files/main.d1ca640c.js
streamlit_ketchersa/frontend/dist/Ketcher v2.9.0_files/main.fbcad79e.css
streamlit_ketchersa/frontend/dist/assets/index-280fb4f0.js