Metadata-Version: 2.1
Name: streamlit-ketchersa
Version: 0.0.2
Summary: This library is a streamlit app for chemical or medical use that open and draw small molecules
Home-page: https://gitlab.com/nicolalandro/streamlit-ketchersa/-/tree/main/
Author: Nicola Landro
Author-email: nicolaxx94@live.it
License: UNKNOWN
Project-URL: Source, https://gitlab.com/nicolalandro/streamlit-ketchersa/-/tree/main/
Keywords: chemistry,molecule,streamlit
Platform: UNKNOWN
Requires-Python: >=3.6
